archivist_samples/__init__.py
archivist_samples/about.py
archivist_samples/door_entry/__init__.py
archivist_samples/door_entry/__main__.py
archivist_samples/door_entry/main.py
archivist_samples/door_entry/run.py
archivist_samples/door_entry/images/__init__.py
archivist_samples/door_entry/images/assets/__init__.py
archivist_samples/door_entry/images/assets/bastille.jpg
archivist_samples/door_entry/images/assets/cityhall.jpg
archivist_samples/door_entry/images/assets/courts.jpg
archivist_samples/door_entry/images/assets/entry_terminal.jpg
archivist_samples/door_entry/images/assets/gdn_front.jpg
archivist_samples/door_entry/images/assets/gdn_side.jpg
archivist_samples/door_entry/images/assets/smartcard.jpg
archivist_samples/door_entry/images/events/__init__.py
archivist_samples/door_entry/images/events/dooropen.png
archivist_samples/estate_info/__init__.py
archivist_samples/estate_info/__main__.py
archivist_samples/estate_info/main.py
archivist_samples/signed_records/__init__.py
archivist_samples/signed_records/__main__.py
archivist_samples/signed_records/main.py
archivist_samples/software_bill_of_materials/__init__.py
archivist_samples/software_bill_of_materials/__main__.py
archivist_samples/software_bill_of_materials/main.py
archivist_samples/software_bill_of_materials/run.py
archivist_samples/software_bill_of_materials/software_deployment.py
archivist_samples/software_bill_of_materials/software_package.py
archivist_samples/software_bill_of_materials/sbom_files/Comp_2.jpeg
archivist_samples/software_bill_of_materials/sbom_files/__init__.py
archivist_samples/software_bill_of_materials/sbom_files/v4_1_5_sbom.xml
archivist_samples/software_bill_of_materials/sbom_files/v4_1_6_1_sbom.xml
archivist_samples/software_bill_of_materials/sbom_files/v4_1_6_sbom.xml
archivist_samples/software_bill_of_materials/sbom_files/v4_1_7_sbom.xml
archivist_samples/software_bill_of_materials/sbom_files/v5_0_0_sbom.xml
archivist_samples/synsation/__init__.py
jitsuin_archivist_samples-0.6.1.dist-info/LICENSE
jitsuin_archivist_samples-0.6.1.dist-info/METADATA
jitsuin_archivist_samples-0.6.1.dist-info/WHEEL
jitsuin_archivist_samples-0.6.1.dist-info/entry_points.txt
jitsuin_archivist_samples-0.6.1.dist-info/top_level.txt
jitsuin_archivist_samples-0.6.1.dist-info/RECORD
