Metadata-Version: 2.1
Name: jitsuin-archivist-samples
Version: 0.6.1
Summary: RKVST Examples
Home-page: https://github.com/jitsuin-inc/archivist-samples
Author: RKVST Inc.
Author-email: support@rkvst.com
License: MIT
Project-URL: Source, https://github.com/jitsuin-inc/archivist-samples
Project-URL: Tracker, https://github.com/jitsuin-inc/archivist-samples/issues
Classifier: Development Status :: 3 - Alpha
Classifier: Environment :: Console
Classifier: Intended Audience :: Developers
Classifier: License :: OSI Approved :: MIT License
Classifier: Operating System :: POSIX :: Linux
Classifier: Programming Language :: Python :: 3.7
Classifier: Topic :: Utilities
Requires-Python: >=3.7
License-File: LICENSE
Requires-Dist: cryptography (~=38.0)
Requires-Dist: jitsuin-archivist (==0.17.5)
Requires-Dist: pyyaml (~=5.4)
